[
  {
    "Id": 1,
    "IsIgnore": null,
    "Memo": "2023_お年玉ログインボーナス",
    "DailyRewardList": [
      {
        "Date": 1,
        "DailyRewardItem": {
          "ItemCount": 10,
          "ItemId": 2,
          "ItemType": "GachaTicket"
        },
        "RarityFlags": 0
      },
      {
        "Date": 2,
        "DailyRewardItem": {
          "ItemCount": 1,
          "ItemId": 15,
          "ItemType": "QuestQuickTicket"
        },
        "RarityFlags": 0
      },
      {
        "Date": 3,
        "DailyRewardItem": {
          "ItemCount": 50,
          "ItemId": 4,
          "ItemType": "ExchangePlaceItem"
        },
        "RarityFlags": 0
      },
      {
        "Date": 4,
        "DailyRewardItem": {
          "ItemCount": 240,
          "ItemId": 27,
          "ItemType": "TreasureChest"
        },
        "RarityFlags": 0
      },
      {
        "Date": 5,
        "DailyRewardItem": {
          "ItemCount": 20,
          "ItemId": 1,
          "ItemType": "TreasureChestKey"
        },
        "RarityFlags": 0
      },
      {
        "Date": 6,
        "DailyRewardItem": {
          "ItemCount": 1,
          "ItemId": 15,
          "ItemType": "QuestQuickTicket"
        },
        "RarityFlags": 0
      },
      {
        "Date": 7,
        "DailyRewardItem": {
          "ItemCount": 10,
          "ItemId": 2,
          "ItemType": "TreasureChestKey"
        },
        "RarityFlags": 0
      },
      {
        "Date": 8,
        "DailyRewardItem": {
          "ItemCount": 5000000,
          "ItemId": 1,
          "ItemType": "Gold"
        },
        "RarityFlags": 0
      },
      {
        "Date": 9,
        "DailyRewardItem": {
          "ItemCount": 5,
          "ItemId": 3,
          "ItemType": "TreasureChestKey"
        },
        "RarityFlags": 0
      },
      {
        "Date": 10,
        "DailyRewardItem": {
          "ItemCount": 3,
          "ItemId": 1,
          "ItemType": "MatchlessSacredTreasureExpItem"
        },
        "RarityFlags": 0
      },
      {
        "Date": 11,
        "DailyRewardItem": {
          "ItemCount": 50,
          "ItemId": 4,
          "ItemType": "ExchangePlaceItem"
        },
        "RarityFlags": 0
      }
    ],
    "ExistEveryDayReward": false,
    "EveryDayRewardItem": null,
    "ExistSpecialReward": true,
    "SpecialRewardItem": {
      "Date": 11,
      "SpecialRewardItem": {
        "ItemCount": 1000,
        "ItemId": 1,
        "ItemType": "CurrencyFree"
      },
      "RarityFlags": 0
    }
  },
  {
    "Id": 2,
    "IsIgnore": null,
    "Memo": "2023_0.5周年ログインボーナス",
    "DailyRewardList": [
      {
        "Date": 1,
        "DailyRewardItem": {
          "ItemCount": 5,
          "ItemId": 2,
          "ItemType": "GachaTicket"
        },
        "RarityFlags": 0
      },
      {
        "Date": 2,
        "DailyRewardItem": {
          "ItemCount": 5,
          "ItemId": 2,
          "ItemType": "GachaTicket"
        },
        "RarityFlags": 0
      },
      {
        "Date": 3,
        "DailyRewardItem": {
          "ItemCount": 5,
          "ItemId": 2,
          "ItemType": "GachaTicket"
        },
        "RarityFlags": 0
      },
      {
        "Date": 4,
        "DailyRewardItem": {
          "ItemCount": 5,
          "ItemId": 2,
          "ItemType": "GachaTicket"
        },
        "RarityFlags": 0
      },
      {
        "Date": 5,
        "DailyRewardItem": {
          "ItemCount": 5,
          "ItemId": 2,
          "ItemType": "GachaTicket"
        },
        "RarityFlags": 0
      },
      {
        "Date": 6,
        "DailyRewardItem": {
          "ItemCount": 5,
          "ItemId": 2,
          "ItemType": "GachaTicket"
        },
        "RarityFlags": 0
      },
      {
        "Date": 7,
        "DailyRewardItem": {
          "ItemCount": 5,
          "ItemId": 2,
          "ItemType": "GachaTicket"
        },
        "RarityFlags": 0
      }
    ],
    "ExistEveryDayReward": false,
    "EveryDayRewardItem": null,
    "ExistSpecialReward": true,
    "SpecialRewardItem": {
      "Date": 7,
      "SpecialRewardItem": {
        "ItemCount": 60,
        "ItemId": 28,
        "ItemType": "TreasureChest"
      },
      "RarityFlags": 0
    }
  },
  {
    "Id": 3,
    "IsIgnore": null,
    "Memo": "2023_サマーログインボーナス",
    "DailyRewardList": [
      {
        "Date": 1,
        "DailyRewardItem": {
          "ItemCount": 10,
          "ItemId": 2,
          "ItemType": "GachaTicket"
        },
        "RarityFlags": 0
      },
      {
        "Date": 2,
        "DailyRewardItem": {
          "ItemCount": 20,
          "ItemId": 1,
          "ItemType": "TreasureChestKey"
        },
        "RarityFlags": 0
      },
      {
        "Date": 3,
        "DailyRewardItem": {
          "ItemCount": 200,
          "ItemId": 2,
          "ItemType": "CharacterTrainingMaterial"
        },
        "RarityFlags": 0
      },
      {
        "Date": 4,
        "DailyRewardItem": {
          "ItemCount": 5,
          "ItemId": 1,
          "ItemType": "BossChallengeTicket"
        },
        "RarityFlags": 0
      },
      {
        "Date": 5,
        "DailyRewardItem": {
          "ItemCount": 10,
          "ItemId": 2,
          "ItemType": "TreasureChestKey"
        },
        "RarityFlags": 0
      },
      {
        "Date": 6,
        "DailyRewardItem": {
          "ItemCount": 50,
          "ItemId": 4,
          "ItemType": "ExchangePlaceItem"
        },
        "RarityFlags": 0
      },
      {
        "Date": 7,
        "DailyRewardItem": {
          "ItemCount": 5,
          "ItemId": 1,
          "ItemType": "TowerBattleTicket"
        },
        "RarityFlags": 0
      },
      {
        "Date": 8,
        "DailyRewardItem": {
          "ItemCount": 5,
          "ItemId": 3,
          "ItemType": "TreasureChestKey"
        },
        "RarityFlags": 0
      },
      {
        "Date": 9,
        "DailyRewardItem": {
          "ItemCount": 50,
          "ItemId": 4,
          "ItemType": "ExchangePlaceItem"
        },
        "RarityFlags": 0
      },
      {
        "Date": 10,
        "DailyRewardItem": {
          "ItemCount": 1,
          "ItemId": 15,
          "ItemType": "QuestQuickTicket"
        },
        "RarityFlags": 0
      },
      {
        "Date": 11,
        "DailyRewardItem": {
          "ItemCount": 10,
          "ItemId": 2,
          "ItemType": "GachaTicket"
        },
        "RarityFlags": 0
      }
    ],
    "ExistEveryDayReward": false,
    "EveryDayRewardItem": null,
    "ExistSpecialReward": true,
    "SpecialRewardItem": {
      "Date": 11,
      "SpecialRewardItem": {
        "ItemCount": 1000,
        "ItemId": 1,
        "ItemType": "CurrencyFree"
      },
      "RarityFlags": 0
    }
  },
  {
    "Id": 4,
    "IsIgnore": null,
    "Memo": "2023_一周年ログインボーナス",
    "DailyRewardList": [
      {
        "Date": 1,
        "DailyRewardItem": {
          "ItemCount": 10,
          "ItemId": 2,
          "ItemType": "GachaTicket"
        },
        "RarityFlags": 0
      },
      {
        "Date": 2,
        "DailyRewardItem": {
          "ItemCount": 10,
          "ItemId": 1,
          "ItemType": "TreasureChestKey"
        },
        "RarityFlags": 0
      },
      {
        "Date": 3,
        "DailyRewardItem": {
          "ItemCount": 10,
          "ItemId": 2,
          "ItemType": "GachaTicket"
        },
        "RarityFlags": 0
      },
      {
        "Date": 4,
        "DailyRewardItem": {
          "ItemCount": 2,
          "ItemId": 14,
          "ItemType": "QuestQuickTicket"
        },
        "RarityFlags": 0
      },
      {
        "Date": 5,
        "DailyRewardItem": {
          "ItemCount": 10,
          "ItemId": 2,
          "ItemType": "GachaTicket"
        },
        "RarityFlags": 0
      },
      {
        "Date": 6,
        "DailyRewardItem": {
          "ItemCount": 5,
          "ItemId": 2,
          "ItemType": "TreasureChestKey"
        },
        "RarityFlags": 0
      },
      {
        "Date": 7,
        "DailyRewardItem": {
          "ItemCount": 10,
          "ItemId": 2,
          "ItemType": "GachaTicket"
        },
        "RarityFlags": 0
      },
      {
        "Date": 8,
        "DailyRewardItem": {
          "ItemCount": 1,
          "ItemId": 15,
          "ItemType": "QuestQuickTicket"
        },
        "RarityFlags": 0
      },
      {
        "Date": 9,
        "DailyRewardItem": {
          "ItemCount": 10,
          "ItemId": 2,
          "ItemType": "GachaTicket"
        },
        "RarityFlags": 0
      },
      {
        "Date": 10,
        "DailyRewardItem": {
          "ItemCount": 5,
          "ItemId": 3,
          "ItemType": "TreasureChestKey"
        },
        "RarityFlags": 0
      },
      {
        "Date": 11,
        "DailyRewardItem": {
          "ItemCount": 10,
          "ItemId": 2,
          "ItemType": "GachaTicket"
        },
        "RarityFlags": 0
      },
      {
        "Date": 12,
        "DailyRewardItem": {
          "ItemCount": 1500,
          "ItemId": 2,
          "ItemType": "CharacterTrainingMaterial"
        },
        "RarityFlags": 0
      },
      {
        "Date": 13,
        "DailyRewardItem": {
          "ItemCount": 15,
          "ItemId": 2,
          "ItemType": "GachaTicket"
        },
        "RarityFlags": 0
      },
      {
        "Date": 14,
        "DailyRewardItem": {
          "ItemCount": 15,
          "ItemId": 2,
          "ItemType": "GachaTicket"
        },
        "RarityFlags": 0
      }
    ],
    "ExistEveryDayReward": false,
    "EveryDayRewardItem": null,
    "ExistSpecialReward": true,
    "SpecialRewardItem": {
      "Date": 14,
      "SpecialRewardItem": {
        "ItemCount": 2000,
        "ItemId": 2,
        "ItemType": "CharacterTrainingMaterial"
      },
      "RarityFlags": 0
    }
  },
  {
    "Id": 5,
    "IsIgnore": null,
    "Memo": "2024_新年の願いログインボーナス",
    "DailyRewardList": [
      {
        "Date": 1,
        "DailyRewardItem": {
          "ItemCount": 10,
          "ItemId": 2,
          "ItemType": "GachaTicket"
        },
        "RarityFlags": 0
      },
      {
        "Date": 2,
        "DailyRewardItem": {
          "ItemCount": 10,
          "ItemId": 1,
          "ItemType": "TreasureChestKey"
        },
        "RarityFlags": 0
      },
      {
        "Date": 3,
        "DailyRewardItem": {
          "ItemCount": 10,
          "ItemId": 2,
          "ItemType": "GachaTicket"
        },
        "RarityFlags": 0
      },
      {
        "Date": 4,
        "DailyRewardItem": {
          "ItemCount": 2,
          "ItemId": 14,
          "ItemType": "QuestQuickTicket"
        },
        "RarityFlags": 0
      },
      {
        "Date": 5,
        "DailyRewardItem": {
          "ItemCount": 10,
          "ItemId": 2,
          "ItemType": "GachaTicket"
        },
        "RarityFlags": 0
      },
      {
        "Date": 6,
        "DailyRewardItem": {
          "ItemCount": 5,
          "ItemId": 2,
          "ItemType": "TreasureChestKey"
        },
        "RarityFlags": 0
      },
      {
        "Date": 7,
        "DailyRewardItem": {
          "ItemCount": 10,
          "ItemId": 2,
          "ItemType": "GachaTicket"
        },
        "RarityFlags": 0
      },
      {
        "Date": 8,
        "DailyRewardItem": {
          "ItemCount": 1,
          "ItemId": 15,
          "ItemType": "QuestQuickTicket"
        },
        "RarityFlags": 0
      },
      {
        "Date": 9,
        "DailyRewardItem": {
          "ItemCount": 10,
          "ItemId": 2,
          "ItemType": "GachaTicket"
        },
        "RarityFlags": 0
      },
      {
        "Date": 10,
        "DailyRewardItem": {
          "ItemCount": 5,
          "ItemId": 3,
          "ItemType": "TreasureChestKey"
        },
        "RarityFlags": 0
      },
      {
        "Date": 11,
        "DailyRewardItem": {
          "ItemCount": 10,
          "ItemId": 2,
          "ItemType": "GachaTicket"
        },
        "RarityFlags": 0
      },
      {
        "Date": 12,
        "DailyRewardItem": {
          "ItemCount": 1500,
          "ItemId": 2,
          "ItemType": "CharacterTrainingMaterial"
        },
        "RarityFlags": 0
      },
      {
        "Date": 13,
        "DailyRewardItem": {
          "ItemCount": 10,
          "ItemId": 2,
          "ItemType": "GachaTicket"
        },
        "RarityFlags": 0
      },
      {
        "Date": 14,
        "DailyRewardItem": {
          "ItemCount": 2000,
          "ItemId": 2,
          "ItemType": "CharacterTrainingMaterial"
        },
        "RarityFlags": 0
      }
    ],
    "ExistEveryDayReward": false,
    "EveryDayRewardItem": null,
    "ExistSpecialReward": true,
    "SpecialRewardItem": {
      "Date": 14,
      "SpecialRewardItem": {
        "ItemCount": 1000,
        "ItemId": 1,
        "ItemType": "CurrencyFree"
      },
      "RarityFlags": 0
    }
  },
  {
    "Id": 6,
    "IsIgnore": null,
    "Memo": "2024_1.5周年記念ログインボーナス",
    "DailyRewardList": [
      {
        "Date": 1,
        "DailyRewardItem": {
          "ItemCount": 1,
          "ItemId": 88,
          "ItemType": "Character"
        },
        "RarityFlags": 8
      },
      {
        "Date": 2,
        "DailyRewardItem": {
          "ItemCount": 5,
          "ItemId": 1,
          "ItemType": "TreasureChestKey"
        },
        "RarityFlags": 0
      },
      {
        "Date": 3,
        "DailyRewardItem": {
          "ItemCount": 10,
          "ItemId": 2,
          "ItemType": "GachaTicket"
        },
        "RarityFlags": 0
      },
      {
        "Date": 4,
        "DailyRewardItem": {
          "ItemCount": 2,
          "ItemId": 14,
          "ItemType": "QuestQuickTicket"
        },
        "RarityFlags": 0
      },
      {
        "Date": 5,
        "DailyRewardItem": {
          "ItemCount": 10,
          "ItemId": 2,
          "ItemType": "GachaTicket"
        },
        "RarityFlags": 0
      },
      {
        "Date": 6,
        "DailyRewardItem": {
          "ItemCount": 5,
          "ItemId": 2,
          "ItemType": "TreasureChestKey"
        },
        "RarityFlags": 0
      },
      {
        "Date": 7,
        "DailyRewardItem": {
          "ItemCount": 10,
          "ItemId": 2,
          "ItemType": "GachaTicket"
        },
        "RarityFlags": 0
      },
      {
        "Date": 8,
        "DailyRewardItem": {
          "ItemCount": 1,
          "ItemId": 15,
          "ItemType": "QuestQuickTicket"
        },
        "RarityFlags": 0
      },
      {
        "Date": 9,
        "DailyRewardItem": {
          "ItemCount": 10,
          "ItemId": 2,
          "ItemType": "GachaTicket"
        },
        "RarityFlags": 0
      },
      {
        "Date": 10,
        "DailyRewardItem": {
          "ItemCount": 5,
          "ItemId": 3,
          "ItemType": "TreasureChestKey"
        },
        "RarityFlags": 0
      },
      {
        "Date": 11,
        "DailyRewardItem": {
          "ItemCount": 750,
          "ItemId": 2,
          "ItemType": "CharacterTrainingMaterial"
        },
        "RarityFlags": 0
      },
      {
        "Date": 12,
        "DailyRewardItem": {
          "ItemCount": 10,
          "ItemId": 2,
          "ItemType": "GachaTicket"
        },
        "RarityFlags": 0
      },
      {
        "Date": 13,
        "DailyRewardItem": {
          "ItemCount": 1500,
          "ItemId": 2,
          "ItemType": "CharacterTrainingMaterial"
        },
        "RarityFlags": 0
      },
      {
        "Date": 14,
        "DailyRewardItem": {
          "ItemCount": 20,
          "ItemId": 2,
          "ItemType": "GachaTicket"
        },
        "RarityFlags": 0
      }
    ],
    "ExistEveryDayReward": false,
    "EveryDayRewardItem": null,
    "ExistSpecialReward": true,
    "SpecialRewardItem": {
      "Date": 10,
      "SpecialRewardItem": {
        "ItemCount": 1,
        "ItemId": 23,
        "ItemType": "SpecialIcon"
      },
      "RarityFlags": 0
    }
  },
  {
    "Id": 7,
    "IsIgnore": null,
    "Memo": "2024_サマーログインボーナス",
    "DailyRewardList": [
      {
        "Date": 1,
        "DailyRewardItem": {
          "ItemCount": 10,
          "ItemId": 2,
          "ItemType": "GachaTicket"
        },
        "RarityFlags": 0
      },
      {
        "Date": 2,
        "DailyRewardItem": {
          "ItemCount": 10,
          "ItemId": 1,
          "ItemType": "TreasureChestKey"
        },
        "RarityFlags": 0
      },
      {
        "Date": 3,
        "DailyRewardItem": {
          "ItemCount": 10,
          "ItemId": 2,
          "ItemType": "GachaTicket"
        },
        "RarityFlags": 0
      },
      {
        "Date": 4,
        "DailyRewardItem": {
          "ItemCount": 2,
          "ItemId": 14,
          "ItemType": "QuestQuickTicket"
        },
        "RarityFlags": 0
      },
      {
        "Date": 5,
        "DailyRewardItem": {
          "ItemCount": 10,
          "ItemId": 2,
          "ItemType": "GachaTicket"
        },
        "RarityFlags": 0
      },
      {
        "Date": 6,
        "DailyRewardItem": {
          "ItemCount": 5,
          "ItemId": 2,
          "ItemType": "TreasureChestKey"
        },
        "RarityFlags": 0
      },
      {
        "Date": 7,
        "DailyRewardItem": {
          "ItemCount": 10,
          "ItemId": 2,
          "ItemType": "GachaTicket"
        },
        "RarityFlags": 0
      },
      {
        "Date": 8,
        "DailyRewardItem": {
          "ItemCount": 1,
          "ItemId": 15,
          "ItemType": "QuestQuickTicket"
        },
        "RarityFlags": 0
      },
      {
        "Date": 9,
        "DailyRewardItem": {
          "ItemCount": 10,
          "ItemId": 2,
          "ItemType": "GachaTicket"
        },
        "RarityFlags": 0
      },
      {
        "Date": 10,
        "DailyRewardItem": {
          "ItemCount": 5,
          "ItemId": 3,
          "ItemType": "TreasureChestKey"
        },
        "RarityFlags": 0
      },
      {
        "Date": 11,
        "DailyRewardItem": {
          "ItemCount": 10,
          "ItemId": 2,
          "ItemType": "GachaTicket"
        },
        "RarityFlags": 0
      },
      {
        "Date": 12,
        "DailyRewardItem": {
          "ItemCount": 1500,
          "ItemId": 2,
          "ItemType": "CharacterTrainingMaterial"
        },
        "RarityFlags": 0
      },
      {
        "Date": 13,
        "DailyRewardItem": {
          "ItemCount": 10,
          "ItemId": 2,
          "ItemType": "GachaTicket"
        },
        "RarityFlags": 0
      },
      {
        "Date": 14,
        "DailyRewardItem": {
          "ItemCount": 2000,
          "ItemId": 2,
          "ItemType": "CharacterTrainingMaterial"
        },
        "RarityFlags": 0
      }
    ],
    "ExistEveryDayReward": false,
    "EveryDayRewardItem": null,
    "ExistSpecialReward": true,
    "SpecialRewardItem": {
      "Date": 14,
      "SpecialRewardItem": {
        "ItemCount": 1000,
        "ItemId": 1,
        "ItemType": "CurrencyFree"
      },
      "RarityFlags": 0
    }
  },
  {
    "Id": 8,
    "IsIgnore": null,
    "Memo": "2024_2周年ログインボーナス",
    "DailyRewardList": [
      {
        "Date": 1,
        "DailyRewardItem": {
          "ItemCount": 10,
          "ItemId": 2,
          "ItemType": "GachaTicket"
        },
        "RarityFlags": 0
      },
      {
        "Date": 2,
        "DailyRewardItem": {
          "ItemCount": 10,
          "ItemId": 1,
          "ItemType": "TreasureChestKey"
        },
        "RarityFlags": 0
      },
      {
        "Date": 3,
        "DailyRewardItem": {
          "ItemCount": 10,
          "ItemId": 2,
          "ItemType": "GachaTicket"
        },
        "RarityFlags": 0
      },
      {
        "Date": 4,
        "DailyRewardItem": {
          "ItemCount": 2,
          "ItemId": 14,
          "ItemType": "QuestQuickTicket"
        },
        "RarityFlags": 0
      },
      {
        "Date": 5,
        "DailyRewardItem": {
          "ItemCount": 10,
          "ItemId": 2,
          "ItemType": "GachaTicket"
        },
        "RarityFlags": 0
      },
      {
        "Date": 6,
        "DailyRewardItem": {
          "ItemCount": 5,
          "ItemId": 2,
          "ItemType": "TreasureChestKey"
        },
        "RarityFlags": 0
      },
      {
        "Date": 7,
        "DailyRewardItem": {
          "ItemCount": 10,
          "ItemId": 2,
          "ItemType": "GachaTicket"
        },
        "RarityFlags": 0
      },
      {
        "Date": 8,
        "DailyRewardItem": {
          "ItemCount": 1,
          "ItemId": 15,
          "ItemType": "QuestQuickTicket"
        },
        "RarityFlags": 0
      },
      {
        "Date": 9,
        "DailyRewardItem": {
          "ItemCount": 10,
          "ItemId": 2,
          "ItemType": "GachaTicket"
        },
        "RarityFlags": 0
      },
      {
        "Date": 10,
        "DailyRewardItem": {
          "ItemCount": 5,
          "ItemId": 3,
          "ItemType": "TreasureChestKey"
        },
        "RarityFlags": 0
      },
      {
        "Date": 11,
        "DailyRewardItem": {
          "ItemCount": 10,
          "ItemId": 2,
          "ItemType": "GachaTicket"
        },
        "RarityFlags": 0
      },
      {
        "Date": 12,
        "DailyRewardItem": {
          "ItemCount": 1500,
          "ItemId": 2,
          "ItemType": "CharacterTrainingMaterial"
        },
        "RarityFlags": 0
      },
      {
        "Date": 13,
        "DailyRewardItem": {
          "ItemCount": 10,
          "ItemId": 2,
          "ItemType": "GachaTicket"
        },
        "RarityFlags": 0
      },
      {
        "Date": 14,
        "DailyRewardItem": {
          "ItemCount": 2000,
          "ItemId": 2,
          "ItemType": "CharacterTrainingMaterial"
        },
        "RarityFlags": 0
      }
    ],
    "ExistEveryDayReward": false,
    "EveryDayRewardItem": null,
    "ExistSpecialReward": true,
    "SpecialRewardItem": {
      "Date": 14,
      "SpecialRewardItem": {
        "ItemCount": 1000,
        "ItemId": 1,
        "ItemType": "CurrencyFree"
      },
      "RarityFlags": 0
    }
  },
  {
    "Id": 9,
    "IsIgnore": null,
    "Memo": "2025_ニューイヤーログインボーナス(2025)",
    "DailyRewardList": [
      {
        "Date": 1,
        "DailyRewardItem": {
          "ItemCount": 10,
          "ItemId": 2,
          "ItemType": "GachaTicket"
        },
        "RarityFlags": 0
      },
      {
        "Date": 2,
        "DailyRewardItem": {
          "ItemCount": 10,
          "ItemId": 1,
          "ItemType": "TreasureChestKey"
        },
        "RarityFlags": 0
      },
      {
        "Date": 3,
        "DailyRewardItem": {
          "ItemCount": 10,
          "ItemId": 2,
          "ItemType": "GachaTicket"
        },
        "RarityFlags": 0
      },
      {
        "Date": 4,
        "DailyRewardItem": {
          "ItemCount": 5,
          "ItemId": 2,
          "ItemType": "MatchlessSacredTreasureExpItem"
        },
        "RarityFlags": 0
      },
      {
        "Date": 5,
        "DailyRewardItem": {
          "ItemCount": 10,
          "ItemId": 2,
          "ItemType": "GachaTicket"
        },
        "RarityFlags": 0
      },
      {
        "Date": 6,
        "DailyRewardItem": {
          "ItemCount": 5,
          "ItemId": 2,
          "ItemType": "TreasureChestKey"
        },
        "RarityFlags": 0
      },
      {
        "Date": 7,
        "DailyRewardItem": {
          "ItemCount": 10,
          "ItemId": 2,
          "ItemType": "GachaTicket"
        },
        "RarityFlags": 0
      },
      {
        "Date": 8,
        "DailyRewardItem": {
          "ItemCount": 500,
          "ItemId": 1,
          "ItemType": "EquipmentReinforcementItem"
        },
        "RarityFlags": 0
      },
      {
        "Date": 9,
        "DailyRewardItem": {
          "ItemCount": 10,
          "ItemId": 2,
          "ItemType": "GachaTicket"
        },
        "RarityFlags": 0
      },
      {
        "Date": 10,
        "DailyRewardItem": {
          "ItemCount": 5,
          "ItemId": 3,
          "ItemType": "TreasureChestKey"
        },
        "RarityFlags": 0
      },
      {
        "Date": 11,
        "DailyRewardItem": {
          "ItemCount": 10,
          "ItemId": 2,
          "ItemType": "GachaTicket"
        },
        "RarityFlags": 0
      },
      {
        "Date": 12,
        "DailyRewardItem": {
          "ItemCount": 1,
          "ItemId": 15,
          "ItemType": "QuestQuickTicket"
        },
        "RarityFlags": 0
      },
      {
        "Date": 13,
        "DailyRewardItem": {
          "ItemCount": 10,
          "ItemId": 2,
          "ItemType": "GachaTicket"
        },
        "RarityFlags": 0
      },
      {
        "Date": 14,
        "DailyRewardItem": {
          "ItemCount": 1,
          "ItemId": 15,
          "ItemType": "QuestQuickTicket"
        },
        "RarityFlags": 0
      }
    ],
    "ExistEveryDayReward": false,
    "EveryDayRewardItem": null,
    "ExistSpecialReward": true,
    "SpecialRewardItem": {
      "Date": 14,
      "SpecialRewardItem": {
        "ItemCount": 1000,
        "ItemId": 1,
        "ItemType": "CurrencyFree"
      },
      "RarityFlags": 0
    }
  },
  {
    "Id": 10,
    "IsIgnore": null,
    "Memo": "2025_2.5周年記念ログインボーナス(2025)",
    "DailyRewardList": [
      {
        "Date": 1,
        "DailyRewardItem": {
          "ItemCount": 10,
          "ItemId": 2,
          "ItemType": "GachaTicket"
        },
        "RarityFlags": 0
      },
      {
        "Date": 2,
        "DailyRewardItem": {
          "ItemCount": 30,
          "ItemId": 1,
          "ItemType": "TreasureChestKey"
        },
        "RarityFlags": 0
      },
      {
        "Date": 3,
        "DailyRewardItem": {
          "ItemCount": 10,
          "ItemId": 2,
          "ItemType": "GachaTicket"
        },
        "RarityFlags": 0
      },
      {
        "Date": 4,
        "DailyRewardItem": {
          "ItemCount": 5,
          "ItemId": 2,
          "ItemType": "MatchlessSacredTreasureExpItem"
        },
        "RarityFlags": 0
      },
      {
        "Date": 5,
        "DailyRewardItem": {
          "ItemCount": 2,
          "ItemId": 14,
          "ItemType": "QuestQuickTicket"
        },
        "RarityFlags": 0
      },
      {
        "Date": 6,
        "DailyRewardItem": {
          "ItemCount": 10,
          "ItemId": 2,
          "ItemType": "GachaTicket"
        },
        "RarityFlags": 0
      },
      {
        "Date": 7,
        "DailyRewardItem": {
          "ItemCount": 1,
          "ItemId": 2,
          "ItemType": "ChatBalloon"
        },
        "RarityFlags": 0
      },
      {
        "Date": 8,
        "DailyRewardItem": {
          "ItemCount": 10,
          "ItemId": 2,
          "ItemType": "GachaTicket"
        },
        "RarityFlags": 0
      },
      {
        "Date": 9,
        "DailyRewardItem": {
          "ItemCount": 2,
          "ItemId": 9,
          "ItemType": "QuestQuickTicket"
        },
        "RarityFlags": 0
      },
      {
        "Date": 10,
        "DailyRewardItem": {
          "ItemCount": 10,
          "ItemId": 2,
          "ItemType": "GachaTicket"
        },
        "RarityFlags": 0
      },
      {
        "Date": 11,
        "DailyRewardItem": {
          "ItemCount": 1000,
          "ItemId": 1,
          "ItemType": "EquipmentReinforcementItem"
        },
        "RarityFlags": 0
      },
      {
        "Date": 12,
        "DailyRewardItem": {
          "ItemCount": 10,
          "ItemId": 2,
          "ItemType": "GachaTicket"
        },
        "RarityFlags": 0
      },
      {
        "Date": 13,
        "DailyRewardItem": {
          "ItemCount": 1,
          "ItemId": 15,
          "ItemType": "QuestQuickTicket"
        },
        "RarityFlags": 0
      },
      {
        "Date": 14,
        "DailyRewardItem": {
          "ItemCount": 15,
          "ItemId": 2,
          "ItemType": "GachaTicket"
        },
        "RarityFlags": 0
      }
    ],
    "ExistEveryDayReward": false,
    "EveryDayRewardItem": null,
    "ExistSpecialReward": true,
    "SpecialRewardItem": {
      "Date": 10,
      "SpecialRewardItem": {
        "ItemCount": 1,
        "ItemId": 1002,
        "ItemType": "ChatEmoticon"
      },
      "RarityFlags": 0
    }
  },
  {
    "Id": 11,
    "IsIgnore": null,
    "Memo": "2025_コルディ（団長）登場記念ログインボーナス",
    "DailyRewardList": [
      {
        "Date": 1,
        "DailyRewardItem": {
          "ItemCount": 10,
          "ItemId": 2,
          "ItemType": "GachaTicket"
        },
        "RarityFlags": 0
      },
      {
        "Date": 2,
        "DailyRewardItem": {
          "ItemCount": 20,
          "ItemId": 1,
          "ItemType": "TreasureChestKey"
        },
        "RarityFlags": 0
      },
      {
        "Date": 3,
        "DailyRewardItem": {
          "ItemCount": 10,
          "ItemId": 2,
          "ItemType": "GachaTicket"
        },
        "RarityFlags": 0
      },
      {
        "Date": 4,
        "DailyRewardItem": {
          "ItemCount": 2,
          "ItemId": 14,
          "ItemType": "QuestQuickTicket"
        },
        "RarityFlags": 0
      },
      {
        "Date": 5,
        "DailyRewardItem": {
          "ItemCount": 5,
          "ItemId": 2,
          "ItemType": "MatchlessSacredTreasureExpItem"
        },
        "RarityFlags": 0
      },
      {
        "Date": 6,
        "DailyRewardItem": {
          "ItemCount": 10,
          "ItemId": 2,
          "ItemType": "GachaTicket"
        },
        "RarityFlags": 0
      },
      {
        "Date": 7,
        "DailyRewardItem": {
          "ItemCount": 30,
          "ItemId": 1,
          "ItemType": "TreasureChestKey"
        },
        "RarityFlags": 0
      },
      {
        "Date": 8,
        "DailyRewardItem": {
          "ItemCount": 10,
          "ItemId": 2,
          "ItemType": "GachaTicket"
        },
        "RarityFlags": 0
      },
      {
        "Date": 9,
        "DailyRewardItem": {
          "ItemCount": 2,
          "ItemId": 9,
          "ItemType": "QuestQuickTicket"
        },
        "RarityFlags": 0
      },
      {
        "Date": 10,
        "DailyRewardItem": {
          "ItemCount": 10,
          "ItemId": 2,
          "ItemType": "GachaTicket"
        },
        "RarityFlags": 0
      },
      {
        "Date": 11,
        "DailyRewardItem": {
          "ItemCount": 30,
          "ItemId": 1,
          "ItemType": "TreasureChestKey"
        },
        "RarityFlags": 0
      },
      {
        "Date": 12,
        "DailyRewardItem": {
          "ItemCount": 10,
          "ItemId": 2,
          "ItemType": "GachaTicket"
        },
        "RarityFlags": 0
      },
      {
        "Date": 13,
        "DailyRewardItem": {
          "ItemCount": 1,
          "ItemId": 15,
          "ItemType": "QuestQuickTicket"
        },
        "RarityFlags": 0
      },
      {
        "Date": 14,
        "DailyRewardItem": {
          "ItemCount": 15,
          "ItemId": 2,
          "ItemType": "GachaTicket"
        },
        "RarityFlags": 0
      }
    ],
    "ExistEveryDayReward": false,
    "EveryDayRewardItem": null,
    "ExistSpecialReward": true,
    "SpecialRewardItem": {
      "Date": 10,
      "SpecialRewardItem": {
        "ItemCount": 1,
        "ItemId": 1005,
        "ItemType": "ChatEmoticon"
      },
      "RarityFlags": 0
    }
  },
  {
    "Id": 12,
    "IsIgnore": null,
    "Memo": "2025_3周年記念ログインボーナス",
    "DailyRewardList": [
      {
        "Date": 1,
        "DailyRewardItem": {
          "ItemCount": 10,
          "ItemId": 2,
          "ItemType": "GachaTicket"
        },
        "RarityFlags": 0
      },
      {
        "Date": 2,
        "DailyRewardItem": {
          "ItemCount": 20,
          "ItemId": 1,
          "ItemType": "TreasureChestKey"
        },
        "RarityFlags": 0
      },
      {
        "Date": 3,
        "DailyRewardItem": {
          "ItemCount": 10,
          "ItemId": 2,
          "ItemType": "GachaTicket"
        },
        "RarityFlags": 0
      },
      {
        "Date": 4,
        "DailyRewardItem": {
          "ItemCount": 5,
          "ItemId": 2,
          "ItemType": "MatchlessSacredTreasureExpItem"
        },
        "RarityFlags": 0
      },
      {
        "Date": 5,
        "DailyRewardItem": {
          "ItemCount": 30,
          "ItemId": 1,
          "ItemType": "TreasureChestKey"
        },
        "RarityFlags": 0
      },
      {
        "Date": 6,
        "DailyRewardItem": {
          "ItemCount": 10,
          "ItemId": 2,
          "ItemType": "GachaTicket"
        },
        "RarityFlags": 0
      },
      {
        "Date": 7,
        "DailyRewardItem": {
          "ItemCount": 1,
          "ItemId": 4,
          "ItemType": "ChatBalloon"
        },
        "RarityFlags": 0
      },
      {
        "Date": 8,
        "DailyRewardItem": {
          "ItemCount": 10,
          "ItemId": 2,
          "ItemType": "GachaTicket"
        },
        "RarityFlags": 0
      },
      {
        "Date": 9,
        "DailyRewardItem": {
          "ItemCount": 1,
          "ItemId": 10,
          "ItemType": "QuestQuickTicket"
        },
        "RarityFlags": 0
      },
      {
        "Date": 10,
        "DailyRewardItem": {
          "ItemCount": 10,
          "ItemId": 2,
          "ItemType": "GachaTicket"
        },
        "RarityFlags": 0
      },
      {
        "Date": 11,
        "DailyRewardItem": {
          "ItemCount": 30,
          "ItemId": 1,
          "ItemType": "TreasureChestKey"
        },
        "RarityFlags": 0
      },
      {
        "Date": 12,
        "DailyRewardItem": {
          "ItemCount": 10,
          "ItemId": 2,
          "ItemType": "GachaTicket"
        },
        "RarityFlags": 0
      },
      {
        "Date": 13,
        "DailyRewardItem": {
          "ItemCount": 1,
          "ItemId": 15,
          "ItemType": "QuestQuickTicket"
        },
        "RarityFlags": 0
      },
      {
        "Date": 14,
        "DailyRewardItem": {
          "ItemCount": 15,
          "ItemId": 2,
          "ItemType": "GachaTicket"
        },
        "RarityFlags": 0
      }
    ],
    "ExistEveryDayReward": false,
    "EveryDayRewardItem": null,
    "ExistSpecialReward": true,
    "SpecialRewardItem": {
      "Date": 14,
      "SpecialRewardItem": {
        "ItemCount": 1,
        "ItemId": 1007,
        "ItemType": "ChatEmoticon"
      },
      "RarityFlags": 0
    }
  },
  {
    "Id": 13,
    "IsIgnore": null,
    "Memo": "2026_ニューイヤーログインボーナス",
    "DailyRewardList": [
      {
        "Date": 1,
        "DailyRewardItem": {
          "ItemCount": 10,
          "ItemId": 2,
          "ItemType": "GachaTicket"
        },
        "RarityFlags": 0
      },
      {
        "Date": 2,
        "DailyRewardItem": {
          "ItemCount": 20,
          "ItemId": 1,
          "ItemType": "TreasureChestKey"
        },
        "RarityFlags": 0
      },
      {
        "Date": 3,
        "DailyRewardItem": {
          "ItemCount": 10,
          "ItemId": 2,
          "ItemType": "GachaTicket"
        },
        "RarityFlags": 0
      },
      {
        "Date": 4,
        "DailyRewardItem": {
          "ItemCount": 20,
          "ItemId": 2,
          "ItemType": "EquipmentReinforcementItem"
        },
        "RarityFlags": 0
      },
      {
        "Date": 5,
        "DailyRewardItem": {
          "ItemCount": 10,
          "ItemId": 2,
          "ItemType": "GachaTicket"
        },
        "RarityFlags": 0
      },
      {
        "Date": 6,
        "DailyRewardItem": {
          "ItemCount": 30,
          "ItemId": 1,
          "ItemType": "TreasureChestKey"
        },
        "RarityFlags": 0
      },
      {
        "Date": 7,
        "DailyRewardItem": {
          "ItemCount": 10,
          "ItemId": 2,
          "ItemType": "GachaTicket"
        },
        "RarityFlags": 0
      },
      {
        "Date": 8,
        "DailyRewardItem": {
          "ItemCount": 1,
          "ItemId": 10,
          "ItemType": "QuestQuickTicket"
        },
        "RarityFlags": 0
      },
      {
        "Date": 9,
        "DailyRewardItem": {
          "ItemCount": 10,
          "ItemId": 2,
          "ItemType": "GachaTicket"
        },
        "RarityFlags": 0
      },
      {
        "Date": 10,
        "DailyRewardItem": {
          "ItemCount": 5,
          "ItemId": 2,
          "ItemType": "MatchlessSacredTreasureExpItem"
        },
        "RarityFlags": 0
      },
      {
        "Date": 11,
        "DailyRewardItem": {
          "ItemCount": 30,
          "ItemId": 1,
          "ItemType": "TreasureChestKey"
        },
        "RarityFlags": 0
      },
      {
        "Date": 12,
        "DailyRewardItem": {
          "ItemCount": 10,
          "ItemId": 2,
          "ItemType": "GachaTicket"
        },
        "RarityFlags": 0
      },
      {
        "Date": 13,
        "DailyRewardItem": {
          "ItemCount": 1,
          "ItemId": 15,
          "ItemType": "QuestQuickTicket"
        },
        "RarityFlags": 0
      },
      {
        "Date": 14,
        "DailyRewardItem": {
          "ItemCount": 15,
          "ItemId": 2,
          "ItemType": "GachaTicket"
        },
        "RarityFlags": 0
      }
    ],
    "ExistEveryDayReward": false,
    "EveryDayRewardItem": null,
    "ExistSpecialReward": true,
    "SpecialRewardItem": {
      "Date": 10,
      "SpecialRewardItem": {
        "ItemCount": 1000,
        "ItemId": 1,
        "ItemType": "CurrencyFree"
      },
      "RarityFlags": 0
    }
  }
]
