[
  {
    "Id": 1,
    "IsIgnore": null,
    "Memo": null,
    "MissionGroupType": "MissionGroupType.Beginner",
    "RequiredClearCount": 5,
    "RewardList": [
      {
        "Item": {
          "ItemType": "ItemType.CurrencyFree",
          "ItemId": 1,
          "ItemCount": 100
        },
        "RarityFlags": "CharacterRarityFlags.None"
      },
      {
        "Item": {
          "ItemType": "ItemType.EquipmentReinforcementItem",
          "ItemId": 1,
          "ItemCount": 100
        },
        "RarityFlags": "CharacterRarityFlags.None"
      }
    ]
  },
  {
    "Id": 2,
    "IsIgnore": null,
    "Memo": null,
    "MissionGroupType": "MissionGroupType.Beginner",
    "RequiredClearCount": 15,
    "RewardList": [
      {
        "Item": {
          "ItemType": "ItemType.CurrencyFree",
          "ItemId": 1,
          "ItemCount": 150
        },
        "RarityFlags": "CharacterRarityFlags.None"
      },
      {
        "Item": {
          "ItemType": "ItemType.Character",
          "ItemId": 5,
          "ItemCount": 1
        },
        "RarityFlags": "CharacterRarityFlags.SR"
      }
    ]
  },
  {
    "Id": 3,
    "IsIgnore": null,
    "Memo": null,
    "MissionGroupType": "MissionGroupType.Beginner",
    "RequiredClearCount": 30,
    "RewardList": [
      {
        "Item": {
          "ItemType": "ItemType.CurrencyFree",
          "ItemId": 1,
          "ItemCount": 200
        },
        "RarityFlags": "CharacterRarityFlags.None"
      },
      {
        "Item": {
          "ItemType": "ItemType.QuestQuickTicket",
          "ItemId": 9,
          "ItemCount": 1
        },
        "RarityFlags": "CharacterRarityFlags.None"
      },
      {
        "Item": {
          "ItemType": "ItemType.QuestQuickTicket",
          "ItemId": 14,
          "ItemCount": 1
        },
        "RarityFlags": "CharacterRarityFlags.None"
      }
    ]
  },
  {
    "Id": 4,
    "IsIgnore": null,
    "Memo": null,
    "MissionGroupType": "MissionGroupType.Beginner",
    "RequiredClearCount": 50,
    "RewardList": [
      {
        "Item": {
          "ItemType": "ItemType.CurrencyFree",
          "ItemId": 1,
          "ItemCount": 300
        },
        "RarityFlags": "CharacterRarityFlags.None"
      },
      {
        "Item": {
          "ItemType": "ItemType.Character",
          "ItemId": 5,
          "ItemCount": 1
        },
        "RarityFlags": "CharacterRarityFlags.SR"
      }
    ]
  },
  {
    "Id": 5,
    "IsIgnore": null,
    "Memo": null,
    "MissionGroupType": "MissionGroupType.Beginner",
    "RequiredClearCount": 70,
    "RewardList": [
      {
        "Item": {
          "ItemType": "ItemType.CurrencyFree",
          "ItemId": 1,
          "ItemCount": 500
        },
        "RarityFlags": "CharacterRarityFlags.None"
      },
      {
        "Item": {
          "ItemType": "ItemType.TreasureChest",
          "ItemId": 26,
          "ItemCount": 1
        },
        "RarityFlags": "CharacterRarityFlags.None"
      }
    ]
  },
  {
    "Id": 6,
    "IsIgnore": null,
    "Memo": null,
    "MissionGroupType": "MissionGroupType.Limited",
    "RequiredClearCount": 5,
    "RewardList": [
      {
        "Item": {
          "ItemType": "ItemType.CurrencyFree",
          "ItemId": 1,
          "ItemCount": 100
        },
        "RarityFlags": "CharacterRarityFlags.None"
      },
      {
        "Item": {
          "ItemType": "ItemType.ExchangePlaceItem",
          "ItemId": 3,
          "ItemCount": 500
        },
        "RarityFlags": "CharacterRarityFlags.None"
      }
    ]
  },
  {
    "Id": 7,
    "IsIgnore": null,
    "Memo": null,
    "MissionGroupType": "MissionGroupType.Limited",
    "RequiredClearCount": 15,
    "RewardList": [
      {
        "Item": {
          "ItemType": "ItemType.CurrencyFree",
          "ItemId": 1,
          "ItemCount": 150
        },
        "RarityFlags": "CharacterRarityFlags.None"
      },
      {
        "Item": {
          "ItemType": "ItemType.GachaTicket",
          "ItemId": 3,
          "ItemCount": 10
        },
        "RarityFlags": "CharacterRarityFlags.None"
      }
    ]
  },
  {
    "Id": 8,
    "IsIgnore": null,
    "Memo": null,
    "MissionGroupType": "MissionGroupType.Limited",
    "RequiredClearCount": 30,
    "RewardList": [
      {
        "Item": {
          "ItemType": "ItemType.CurrencyFree",
          "ItemId": 1,
          "ItemCount": 200
        },
        "RarityFlags": "CharacterRarityFlags.None"
      },
      {
        "Item": {
          "ItemType": "ItemType.QuestQuickTicket",
          "ItemId": 17,
          "ItemCount": 2
        },
        "RarityFlags": "CharacterRarityFlags.None"
      }
    ]
  },
  {
    "Id": 9,
    "IsIgnore": null,
    "Memo": null,
    "MissionGroupType": "MissionGroupType.Limited",
    "RequiredClearCount": 50,
    "RewardList": [
      {
        "Item": {
          "ItemType": "ItemType.CurrencyFree",
          "ItemId": 1,
          "ItemCount": 300
        },
        "RarityFlags": "CharacterRarityFlags.None"
      },
      {
        "Item": {
          "ItemType": "ItemType.GachaTicket",
          "ItemId": 3,
          "ItemCount": 10
        },
        "RarityFlags": "CharacterRarityFlags.None"
      }
    ]
  },
  {
    "Id": 10,
    "IsIgnore": null,
    "Memo": null,
    "MissionGroupType": "MissionGroupType.Limited",
    "RequiredClearCount": 70,
    "RewardList": [
      {
        "Item": {
          "ItemType": "ItemType.CurrencyFree",
          "ItemId": 1,
          "ItemCount": 500
        },
        "RarityFlags": "CharacterRarityFlags.None"
      },
      {
        "Item": {
          "ItemType": "ItemType.TreasureChest",
          "ItemId": 26,
          "ItemCount": 1
        },
        "RarityFlags": "CharacterRarityFlags.None"
      }
    ]
  }
]
